{
  "areas": [
    { "id": "us-ms-adams-county", "name": "Adams County", "state": "ms", "type": "county" },
    { "id": "us-ms-alcorn-county", "name": "Alcorn County", "state": "ms", "type": "county" },
    { "id": "us-ms-amite-county", "name": "Amite County", "state": "ms", "type": "county" },
    { "id": "us-ms-attala-county", "name": "Attala County", "state": "ms", "type": "county" },
    { "id": "us-ms-benton-county", "name": "Benton County", "state": "ms", "type": "county" },
    { "id": "us-ms-bolivar-county", "name": "Bolivar County", "state": "ms", "type": "county" },
    { "id": "us-ms-calhoun-county", "name": "Calhoun County", "state": "ms", "type": "county" },
    { "id": "us-ms-carroll-county", "name": "Carroll County", "state": "ms", "type": "county" },
    { "id": "us-ms-chickasaw-county", "name": "Chickasaw County", "state": "ms", "type": "county" },
    { "id": "us-ms-choctaw-county", "name": "Choctaw County", "state": "ms", "type": "county" },
    { "id": "us-ms-claiborne-county", "name": "Claiborne County", "state": "ms", "type": "county" },
    { "id": "us-ms-clarke-county", "name": "Clarke County", "state": "ms", "type": "county" },
    { "id": "us-ms-clay-county", "name": "Clay County", "state": "ms", "type": "county" },
    { "id": "us-ms-coahoma-county", "name": "Coahoma County", "state": "ms", "type": "county" },
    { "id": "us-ms-copiah-county", "name": "Copiah County", "state": "ms", "type": "county" },
    { "id": "us-ms-covington-county", "name": "Covington County", "state": "ms", "type": "county" },
    { "id": "us-ms-desoto-county", "name": "DeSoto County", "state": "ms", "type": "county" },
    { "id": "us-ms-forrest-county", "name": "Forrest County", "state": "ms", "type": "county" },
    { "id": "us-ms-franklin-county", "name": "Franklin County", "state": "ms", "type": "county" },
    { "id": "us-ms-george-county", "name": "George County", "state": "ms", "type": "county" },
    { "id": "us-ms-greene-county", "name": "Greene County", "state": "ms", "type": "county" },
    { "id": "us-ms-grenada-county", "name": "Grenada County", "state": "ms", "type": "county" },
    { "id": "us-ms-hancock-county", "name": "Hancock County", "state": "ms", "type": "county" },
    { "id": "us-ms-harrison-county", "name": "Harrison County", "state": "ms", "type": "county" },
    { "id": "us-ms-hinds-county", "name": "Hinds County", "state": "ms", "type": "county" },
    { "id": "us-ms-holmes-county", "name": "Holmes County", "state": "ms", "type": "county" },
    { "id": "us-ms-humphreys-county", "name": "Humphreys County", "state": "ms", "type": "county" },
    { "id": "us-ms-issaquena-county", "name": "Issaquena County", "state": "ms", "type": "county" },
    { "id": "us-ms-itawamba-county", "name": "Itawamba County", "state": "ms", "type": "county" },
    { "id": "us-ms-jackson-county", "name": "Jackson County", "state": "ms", "type": "county" },
    { "id": "us-ms-jasper-county", "name": "Jasper County", "state": "ms", "type": "county" },
    { "id": "us-ms-jefferson-county", "name": "Jefferson County", "state": "ms", "type": "county" },
    { "id": "us-ms-jefferson-davis-county", "name": "Jefferson Davis County", "state": "ms", "type": "county" },
    { "id": "us-ms-jones-county", "name": "Jones County", "state": "ms", "type": "county" },
    { "id": "us-ms-kemper-county", "name": "Kemper County", "state": "ms", "type": "county" },
    { "id": "us-ms-lafayette-county", "name": "Lafayette County", "state": "ms", "type": "county" },
    { "id": "us-ms-lamar-county", "name": "Lamar County", "state": "ms", "type": "county" },
    { "id": "us-ms-lauderdale-county", "name": "Lauderdale County", "state": "ms", "type": "county" },
    { "id": "us-ms-lawrence-county", "name": "Lawrence County", "state": "ms", "type": "county" },
    { "id": "us-ms-leake-county", "name": "Leake County", "state": "ms", "type": "county" },
    { "id": "us-ms-lee-county", "name": "Lee County", "state": "ms", "type": "county" },
    { "id": "us-ms-leflore-county", "name": "Leflore County", "state": "ms", "type": "county" },
    { "id": "us-ms-lincoln-county", "name": "Lincoln County", "state": "ms", "type": "county" },
    { "id": "us-ms-lowndes-county", "name": "Lowndes County", "state": "ms", "type": "county" },
    { "id": "us-ms-madison-county", "name": "Madison County", "state": "ms", "type": "county" },
    { "id": "us-ms-marion-county", "name": "Marion County", "state": "ms", "type": "county" },
    { "id": "us-ms-marshall-county", "name": "Marshall County", "state": "ms", "type": "county" },
    { "id": "us-ms-monroe-county", "name": "Monroe County", "state": "ms", "type": "county" },
    { "id": "us-ms-montgomery-county", "name": "Montgomery County", "state": "ms", "type": "county" },
    { "id": "us-ms-neshoba-county", "name": "Neshoba County", "state": "ms", "type": "county" },
    { "id": "us-ms-newton-county", "name": "Newton County", "state": "ms", "type": "county" },
    { "id": "us-ms-noxubee-county", "name": "Noxubee County", "state": "ms", "type": "county" },
    { "id": "us-ms-oktibbeha-county", "name": "Oktibbeha County", "state": "ms", "type": "county" },
    { "id": "us-ms-panola-county", "name": "Panola County", "state": "ms", "type": "county" },
    { "id": "us-ms-pearl-river-county", "name": "Pearl River County", "state": "ms", "type": "county" },
    { "id": "us-ms-perry-county", "name": "Perry County", "state": "ms", "type": "county" },
    { "id": "us-ms-pike-county", "name": "Pike County", "state": "ms", "type": "county" },
    { "id": "us-ms-pontotoc-county", "name": "Pontotoc County", "state": "ms", "type": "county" },
    { "id": "us-ms-prentiss-county", "name": "Prentiss County", "state": "ms", "type": "county" },
    { "id": "us-ms-quitman-county", "name": "Quitman County", "state": "ms", "type": "county" },
    { "id": "us-ms-rankin-county", "name": "Rankin County", "state": "ms", "type": "county" },
    { "id": "us-ms-scott-county", "name": "Scott County", "state": "ms", "type": "county" },
    { "id": "us-ms-sharkey-county", "name": "Sharkey County", "state": "ms", "type": "county" },
    { "id": "us-ms-simpson-county", "name": "Simpson County", "state": "ms", "type": "county" },
    { "id": "us-ms-smith-county", "name": "Smith County", "state": "ms", "type": "county" },
    { "id": "us-ms-stone-county", "name": "Stone County", "state": "ms", "type": "county" },
    { "id": "us-ms-sunflower-county", "name": "Sunflower County", "state": "ms", "type": "county" },
    { "id": "us-ms-tallahatchie-county", "name": "Tallahatchie County", "state": "ms", "type": "county" },
    { "id": "us-ms-tate-county", "name": "Tate County", "state": "ms", "type": "county" },
    { "id": "us-ms-tippah-county", "name": "Tippah County", "state": "ms", "type": "county" },
    { "id": "us-ms-tishomingo-county", "name": "Tishomingo County", "state": "ms", "type": "county" },
    { "id": "us-ms-tunica-county", "name": "Tunica County", "state": "ms", "type": "county" },
    { "id": "us-ms-union-county", "name": "Union County", "state": "ms", "type": "county" },
    { "id": "us-ms-walthall-county", "name": "Walthall County", "state": "ms", "type": "county" },
    { "id": "us-ms-warren-county", "name": "Warren County", "state": "ms", "type": "county" },
    { "id": "us-ms-washington-county", "name": "Washington County", "state": "ms", "type": "county" },
    { "id": "us-ms-wayne-county", "name": "Wayne County", "state": "ms", "type": "county" },
    { "id": "us-ms-webster-county", "name": "Webster County", "state": "ms", "type": "county" },
    { "id": "us-ms-wilkinson-county", "name": "Wilkinson County", "state": "ms", "type": "county" },
    { "id": "us-ms-winston-county", "name": "Winston County", "state": "ms", "type": "county" },
    { "id": "us-ms-yalobusha-county", "name": "Yalobusha County", "state": "ms", "type": "county" },
    { "id": "us-ms-yazoo-county", "name": "Yazoo County", "state": "ms", "type": "county" }
  ]
}